all_purpose_set/__init__.py
all_purpose_set/_vendor/__init__.py
all_purpose_set/_vendor/ordered_set-3.1.1-py3.7.egg-info/PKG-INFO
all_purpose_set/_vendor/ordered_set-3.1.1-py3.7.egg-info/SOURCES.txt
all_purpose_set/_vendor/ordered_set-3.1.1-py3.7.egg-info/dependency_links.txt
all_purpose_set/_vendor/ordered_set-3.1.1-py3.7.egg-info/installed-files.txt
all_purpose_set/_vendor/ordered_set-3.1.1-py3.7.egg-info/top_level.txt
all_purpose_set/_vendor/ordered_set.py
all_purpose_set/_vendor/tedent/__init__.py
all_purpose_set/_vendor/tedent/_vendor/__init__.py
all_purpose_set/_vendor/tedent/_vendor/ordered_set-3.1.1-py3.7.egg-info/PKG-INFO
all_purpose_set/_vendor/tedent/_vendor/ordered_set-3.1.1-py3.7.egg-info/SOURCES.txt
all_purpose_set/_vendor/tedent/_vendor/ordered_set-3.1.1-py3.7.egg-info/dependency_links.txt
all_purpose_set/_vendor/tedent/_vendor/ordered_set-3.1.1-py3.7.egg-info/installed-files.txt
all_purpose_set/_vendor/tedent/_vendor/ordered_set-3.1.1-py3.7.egg-info/top_level.txt
all_purpose_set/_vendor/tedent/_vendor/ordered_set.py
all_purpose_set/_vendor/tedent/_vendor/wrapt/__init__.py
all_purpose_set/_vendor/tedent/_vendor/wrapt/_wrappers.cpython-37m-x86_64-linux-gnu.so
all_purpose_set/_vendor/tedent/_vendor/wrapt/decorators.py
all_purpose_set/_vendor/tedent/_vendor/wrapt/importer.py
all_purpose_set/_vendor/tedent/_vendor/wrapt/wrappers.py
all_purpose_set/_vendor/tedent/_vendor/wrapt-1.11.1.dist-info/INSTALLER
all_purpose_set/_vendor/tedent/_vendor/wrapt-1.11.1.dist-info/LICENSE
all_purpose_set/_vendor/tedent/_vendor/wrapt-1.11.1.dist-info/METADATA
all_purpose_set/_vendor/tedent/_vendor/wrapt-1.11.1.dist-info/RECORD
all_purpose_set/_vendor/tedent/_vendor/wrapt-1.11.1.dist-info/WHEEL
all_purpose_set/_vendor/tedent/_vendor/wrapt-1.11.1.dist-info/top_level.txt
all_purpose_set/_vendor/tedent/fns/__init__.py
all_purpose_set/_vendor/tedent/fns/all_.py
all_purpose_set/_vendor/tedent/fns/decorators/__init__.py
all_purpose_set/_vendor/tedent/fns/decorators/argIsCallable.py
all_purpose_set/_vendor/tedent/fns/decorators/argIsClass.py
all_purpose_set/_vendor/tedent/fns/decorators/argIsListOfType.py
all_purpose_set/_vendor/tedent/fns/decorators/argIsType.py
all_purpose_set/_vendor/tedent/fns/discardFirst.py
all_purpose_set/_vendor/tedent/fns/discardLastWhile.py
all_purpose_set/_vendor/tedent/fns/forEach.py
all_purpose_set/_vendor/tedent/fns/iif.py
all_purpose_set/_vendor/tedent/fns/internal/__init__.py
all_purpose_set/_vendor/tedent/fns/internal/discardWhen.py
all_purpose_set/_vendor/tedent/fns/internal/get.py
all_purpose_set/_vendor/tedent/fns/internal/getArgName.py
all_purpose_set/_vendor/tedent/fns/internal/getFnSignature.py
all_purpose_set/_vendor/tedent/fns/internal/getNumPositionalParams.py
all_purpose_set/_vendor/tedent/fns/internal/getTypedResult.py
all_purpose_set/_vendor/tedent/fns/internal/iif.py
all_purpose_set/_vendor/tedent/fns/internal/isLaden.py
all_purpose_set/_vendor/tedent/fns/internal/isOnlyWhitespace.py
all_purpose_set/_vendor/tedent/fns/internal/isType.py
all_purpose_set/_vendor/tedent/fns/internal/joinWith.py
all_purpose_set/_vendor/tedent/fns/internal/makeCallFn.py
all_purpose_set/_vendor/tedent/fns/internal/makeGenericCallFn.py
all_purpose_set/_vendor/tedent-0.1.5.dist-info/INSTALLER
all_purpose_set/_vendor/tedent-0.1.5.dist-info/METADATA
all_purpose_set/_vendor/tedent-0.1.5.dist-info/RECORD
all_purpose_set/_vendor/tedent-0.1.5.dist-info/WHEEL
all_purpose_set/_vendor/tedent-0.1.5.dist-info/top_level.txt
all_purpose_set/_vendor/wrapt-1.10.11.dist-info/INSTALLER
all_purpose_set/_vendor/wrapt-1.10.11.dist-info/LICENSE
all_purpose_set/_vendor/wrapt-1.10.11.dist-info/METADATA
all_purpose_set/_vendor/wrapt-1.10.11.dist-info/RECORD
all_purpose_set/_vendor/wrapt-1.10.11.dist-info/WHEEL
all_purpose_set/_vendor/wrapt-1.10.11.dist-info/top_level.txt
all_purpose_set-0.1.9.dist-info/WHEEL
all_purpose_set-0.1.9.dist-info/METADATA
all_purpose_set-0.1.9.dist-info/RECORD
