Metadata-Version: 2.1
Name: all-purpose-set
Version: 0.1.9
Summary: A set that works with both hashable and non-hashable elements
Home-page: https://github.com/olsonpm/py_all-purpose-set
Author: Philip Olson
Author-email: philip.olson@pm.me
Requires-Python: >=3.7,<4.0
Classifier: Programming Language :: Python :: 3
Classifier: Programming Language :: Python :: 3.7
Project-URL: Repository, https://github.com/olsonpm/py_all-purpose-set
